wire_size/__init__.py
wire_size/cmd.py
wire_size/downloader/__init__.py
wire_size/downloader/downloader.py
wire_size/downloader/multi_downloader.py
wire_size/downloader/single_downloader.py
wire_size/downloader/utils.py
wire_size/provider/__init__.py
wire_size/provider/digitalocean.py
wire_size/provider/provider.py
wire_size-0.1.0.dist-info/LICENSE
wire_size-0.1.0.dist-info/METADATA
wire_size-0.1.0.dist-info/WHEEL
wire_size-0.1.0.dist-info/entry_points.txt
wire_size-0.1.0.dist-info/top_level.txt
wire_size-0.1.0.dist-info/RECORD
