Metadata-Version: 2.1
Name: wire-size
Version: 0.1.0
Summary: Test bandwidth to cloud provider endpoint.
Author-email: Zxilly <zxilly@outlook.com>
License: GPL-3.0-only
Requires-Python: >=3.8
License-File: LICENSE
Requires-Dist: click (>=8.1.3)
Requires-Dist: tqdm (>=4.64.1)
Requires-Dist: prettytable (>=3.5.0)
Requires-Dist: aiohttp (>=3.8.3)
Requires-Dist: termcolor (>=2.1.1)
Requires-Dist: requests (>=2.28.1)
